Metadata-Version: 2.1
Name: evmTools_pipi
Version: 0.1.0
Summary: evmtools is a toolkit for developing and testing evm.
Home-page: https://github.com/chenyuan07gis/evmTools
Author: Awesome Soul
Author-email: chenyuan07gis@gmail.com
License: MIT
Classifier: License :: OSI Approved :: MIT License
Classifier: Programming Language :: Python
Classifier: Programming Language :: Python :: 3
Classifier: Programming Language :: Python :: 3.6
Classifier: Programming Language :: Python :: Implementation :: CPython
Classifier: Programming Language :: Python :: Implementation :: PyPy
Requires-Python: >=3.10.0
License-File: LICENSE
